flexopus/__init__.py
flexopus/api.py
flexopus-0.0.4.dist-info/LICENSE
flexopus-0.0.4.dist-info/METADATA
flexopus-0.0.4.dist-info/WHEEL
flexopus-0.0.4.dist-info/top_level.txt
flexopus-0.0.4.dist-info/RECORD
