Metadata-Version: 2.1
Name: flexopus
Version: 0.0.4
Summary: Python package to interact with th Flexopus API
Home-page: https://github.com/flexopus/flexopus-python-api
Author: Sebi Nemeth
Author-email: sebezhetetlen98@gmail.com
Classifier: Programming Language :: Python :: 3
Classifier: License :: OSI Approved :: MIT License
Classifier: Operating System :: OS Independent
License-File: LICENSE
Requires-Dist: aiohttp
